facile_rs/__init__.py
facile_rs/_version.py
facile_rs/create_bag.py
facile_rs/create_bagpack.py
facile_rs/create_cff.py
facile_rs/create_datacite.py
facile_rs/create_radar.py
facile_rs/create_release.py
facile_rs/create_zenodo.py
facile_rs/prepare_radar.py
facile_rs/prepare_release.py
facile_rs/prepare_zenodo.py
facile_rs/run_bibtex_pipeline.py
facile_rs/run_docstring_pipeline.py
facile_rs/run_markdown_pipeline.py
facile_rs/tests/bag-info.yml
facile_rs/tests/cff_ref.cff
facile_rs/tests/conftest.py
facile_rs/tests/datacite_ref.xml
facile_rs/tests/test_create_bag.py
facile_rs/tests/test_create_bagpack.py
facile_rs/tests/test_create_cff.py
facile_rs/tests/test_create_datacite.py
facile_rs/tests/test_create_radar.py
facile_rs/tests/test_create_release.py
facile_rs/tests/test_create_zenodo.py
facile_rs/tests/test_prepare_radar.py
facile_rs/tests/test_prepare_release.py
facile_rs/tests/test_prepare_zenodo.py
facile_rs/utils/__init__.py
facile_rs/utils/checksum.py
facile_rs/utils/cli.py
facile_rs/utils/exceptions.py
facile_rs/utils/grav.py
facile_rs/utils/http.py
facile_rs/utils/mail.py
facile_rs/utils/radar.py
facile_rs/utils/zenodo.py
facile_rs/utils/metadata/__init__.py
facile_rs/utils/metadata/cff.py
facile_rs/utils/metadata/codemeta.py
facile_rs/utils/metadata/datacite.py
facile_rs/utils/metadata/radar.py
facile_rs/utils/metadata/zenodo.py
facile_rs/utils/metadata/tests/cff_ref.yml
facile_rs/utils/metadata/tests/codemeta_authors_test.json
facile_rs/utils/metadata/tests/codemeta_contributors_test.json
facile_rs/utils/metadata/tests/codemeta_schemaorg_test.json
facile_rs/utils/metadata/tests/codemeta_test.json
facile_rs/utils/metadata/tests/datacite_ref.xml
facile_rs/utils/metadata/tests/datacite_schemaorg_funding_ref.xml
facile_rs/utils/metadata/tests/test_cff.py
facile_rs/utils/metadata/tests/test_codemeta.py
facile_rs/utils/metadata/tests/test_datacite.py
facile_rs/utils/metadata/tests/test_zenodo.py
facile_rs/utils/tests/test_zenodo_utils.py
facile_rs-3.3.0.dist-info/licenses/LICENSE
facile_rs-3.3.0.dist-info/licenses/NOTICE
facile_rs-3.3.0.dist-info/METADATA
facile_rs-3.3.0.dist-info/WHEEL
facile_rs-3.3.0.dist-info/entry_points.txt
facile_rs-3.3.0.dist-info/top_level.txt
facile_rs-3.3.0.dist-info/RECORD
