Metadata-Version: 2.4
Name: FACILE-RS
Version: 3.3.0
Summary: FACILE-RS (Findability and Accessibility through Continuous Integration with Less Effort) automates tasks around the archival and long term preservation of software repositories.
Author: Marie Houillon, Axel Loewe, Tomas Stary
Author-email: openCARP consortium <info@opencarp.org>, Jochen Klar <mail@jochenklar.de>
Maintainer-email: Jochen Klar <mail@jochenklar.de>
License: 
Project-URL: repository, https://git.opencarp.org/openCARP/FACILE-RS
Classifier: Development Status :: 5 - Production/Stable
Classifier: Environment :: Web Environment
Classifier: Intended Audience :: Science/Research
Classifier: License :: OSI Approved :: Apache Software License
Classifier: Operating System :: OS Independent
Classifier: Programming Language :: Python :: 3 :: Only
Classifier: Programming Language :: Python :: 3.9
Classifier: Programming Language :: Python :: 3.10
Classifier: Programming Language :: Python :: 3.11
Classifier: Programming Language :: Python :: 3.12
Classifier: Programming Language :: Python :: 3.13
Requires-Python: >=3.9
License-File: LICENSE
License-File: NOTICE
Requires-Dist: bagit~=1.7
Requires-Dist: pypandoc~=1.6
Requires-Dist: python-dotenv~=1.1
Requires-Dist: python-frontmatter~=1.1
Requires-Dist: PyYaml~=6.0.2
Requires-Dist: requests~=2.23
Requires-Dist: python-resize-image~=1.1.20
Requires-Dist: Pillow~=9.4.0; python_version <= "3.11"
Requires-Dist: Pillow~=11.0; python_version > "3.11"
Requires-Dist: setuptools
Provides-Extra: dev
Requires-Dist: build; extra == "dev"
Requires-Dist: pre-commit; extra == "dev"
Requires-Dist: ruff; extra == "dev"
Requires-Dist: twine; extra == "dev"
Provides-Extra: test
Requires-Dist: pytest; extra == "test"
Requires-Dist: pytest-cov; extra == "test"
Requires-Dist: coverage; extra == "test"
Requires-Dist: cffconvert; extra == "test"
Dynamic: license-file
